README.rst
setup.py
dutch_boy/__init__.py
dutch_boy.egg-info/PKG-INFO
dutch_boy.egg-info/SOURCES.txt
dutch_boy.egg-info/dependency_links.txt
dutch_boy.egg-info/entry_points.txt
dutch_boy.egg-info/requires.txt
dutch_boy.egg-info/top_level.txt
dutch_boy/nose/__init__.py
dutch_boy/nose/plugin.py
dutch_boy/nose/test/__init__.py
dutch_boy/nose/test/plugin_test.py